{
  "entries": {
    "Back": {
      "translation": "Zurück",
      "timestamp": 1765576801
    },
    "Browse beautiful AI-generated images created by our community members, get inspired, and discover amazing artworks": {
      "translation": "Stöbern Sie in den wunderschönen, von unseren Community-Mitgliedern erstellten KI-generierten Bildern, lassen Sie sich inspirieren und entdecken Sie erstaunliche Kunstwerke.",
      "timestamp": 1765576801
    },
    "Create Similar": {
      "translation": "Ähnliche erstellen",
      "timestamp": 1765576801
    },
    "Created": {
      "translation": "Erstellt",
      "timestamp": 1765576801
    },
    "Creative Community - Explore Amazing AI Art": {
      "translation": "Kreativ-Community - Erleben Sie erstaunliche AI-Kunst",
      "timestamp": 1765576801
    },
    "Explore amazing creations from our community and discover your inspiration": {
      "translation": "Entdecken Sie die erstaunlichen Kreationen unserer Community und lassen Sie sich inspirieren",
      "timestamp": 1765576801
    },
    "Failed to load content, please try again": {
      "translation": "Der Inhalt konnte nicht geladen werden, bitte versuchen Sie es erneut",
      "timestamp": 1765576801
    },
    "I'm 18+, Show Content": {
      "translation": "Ich bin 18+, Inhalt anzeigen",
      "timestamp": 1765576801
    },
    "Load More": {
      "translation": "Mehr laden",
      "timestamp": 1765576801
    },
    "No Artworks Yet": {
      "translation": "Noch keine Kunstwerke",
      "timestamp": 1765576801
    },
    "No more items": {
      "translation": "Keine weiteren Artikel",
      "timestamp": 1765576801
    },
    "No public artworks shared yet. Be the first to share your creation!": {
      "translation": "Noch keine öffentlichen Kunstwerke freigegeben. Seien Sie der Erste, der seine Kreation teilt!",
      "timestamp": 1765576801
    },
    "Retry": {
      "translation": "Wiederholung",
      "timestamp": 1765576801
    },
    "Sensitive Content": {
      "translation": "Sensibler Inhalt",
      "timestamp": 1765576801
    },
    "Sensitive Content Warning": {
      "translation": "Warnung vor sensiblen Inhalten",
      "timestamp": 1765576801
    },
    "Start Creating": {
      "translation": "Erstellen beginnen",
      "timestamp": 1765576801
    },
    "This content may contain adult or sensitive material. Please confirm that you are 18+ years old before viewing.": {
      "translation": "Dieser Inhalt kann nicht jugendfreies oder sensibles Material enthalten. Bitte vergewissern Sie sich, dass Sie über 18 Jahre alt sind, bevor Sie ihn ansehen.",
      "timestamp": 1765576801
    },
    "View Details": {
      "translation": "Details anzeigen",
      "timestamp": 1765576801
    }
  }
}