{
  "entries": {
    "Back": {
      "translation": "뒤로",
      "timestamp": 1765580346
    },
    "Browse beautiful AI-generated images created by our community members, get inspired, and discover amazing artworks": {
      "translation": "커뮤니티 회원들이 만든 아름다운 AI 생성 이미지를 둘러보고, 영감을 얻고, 놀라운 예술 작품을 발견하세요.",
      "timestamp": 1765580346
    },
    "Create Similar": {
      "translation": "유사 항목 만들기",
      "timestamp": 1765580346
    },
    "Created": {
      "translation": "생성됨",
      "timestamp": 1765580346
    },
    "Creative Community - Explore Amazing AI Art": {
      "translation": "크리에이티브 커뮤니티 - 놀라운 AI 아트 살펴보기",
      "timestamp": 1765580346
    },
    "Explore amazing creations from our community and discover your inspiration": {
      "translation": "커뮤니티의 놀라운 창작물을 살펴보고 영감을 얻으세요.",
      "timestamp": 1765580346
    },
    "Failed to load content, please try again": {
      "translation": "콘텐츠를 로드하지 못했습니다. 다시 시도하세요.",
      "timestamp": 1765580346
    },
    "I'm 18+, Show Content": {
      "translation": "18세 이상, 콘텐츠 표시",
      "timestamp": 1765580346
    },
    "Load More": {
      "translation": "더 보기",
      "timestamp": 1765580346
    },
    "No Artworks Yet": {
      "translation": "아직 작품 없음",
      "timestamp": 1765580346
    },
    "No more items": {
      "translation": "더 이상 항목 없음",
      "timestamp": 1765580346
    },
    "No public artworks shared yet. Be the first to share your creation!": {
      "translation": "아직 공유된 공개 작품이 없습니다. 가장 먼저 작품을 공유하세요!",
      "timestamp": 1765580346
    },
    "Retry": {
      "translation": "다시 시도",
      "timestamp": 1765580346
    },
    "Sensitive Content": {
      "translation": "민감한 콘텐츠",
      "timestamp": 1765580346
    },
    "Sensitive Content Warning": {
      "translation": "민감한 콘텐츠 경고",
      "timestamp": 1765580346
    },
    "Start Creating": {
      "translation": "만들기 시작",
      "timestamp": 1765580346
    },
    "This content may contain adult or sensitive material. Please confirm that you are 18+ years old before viewing.": {
      "translation": "이 콘텐츠에는 성인용 또는 민감한 내용이 포함되어 있을 수 있습니다. 시청하기 전에 만 18세 이상임을 확인해 주세요.",
      "timestamp": 1765580346
    },
    "View Details": {
      "translation": "세부 정보 보기",
      "timestamp": 1765580346
    }
  }
}